{
  "metadata": {
    "title": "第八章 神經系統",
    "subject": "解剖生理學",
    "chapter": "8",
    "section": "8.1-8.5",
    "topic": "Nervous System",
    "description": "神經系統總論、神經組織、神經生理、中樞神經系統、周邊神經系統、自主神經系統",
    "total_questions": 50,
    "version": "1.0",
    "created_date": "2026-01-07"
  },
  "questions": [
    {"id": 1, "question": "中樞神經系統(CNS)包括？", "question_image": null, "options": {"A": "腦和脊髓", "B": "腦神經和脊神經", "C": "交感神經和副交感神經", "D": "感覺神經和運動神經"}, "options_image": null},
    {"id": 2, "question": "周邊神經系統(PNS)包括？", "question_image": null, "options": {"A": "腦和脊髓", "B": "腦神經和脊神經", "C": "大腦和小腦", "D": "腦幹和間腦"}, "options_image": null},
    {"id": 3, "question": "神經系統的三大功能不包括下列何者？", "question_image": null, "options": {"A": "感覺", "B": "整合", "C": "分泌", "D": "運動"}, "options_image": null},
    {"id": 4, "question": "下列何者屬於中樞神經系統的神經膠細胞？", "question_image": null, "options": {"A": "許旺氏細胞", "B": "衛星細胞", "C": "星形膠細胞", "D": "以上皆是"}, "options_image": null},
    {"id": 5, "question": "形成血腦障壁的神經膠細胞是？", "question_image": null, "options": {"A": "寡突膠細胞", "B": "星形膠細胞", "C": "微膠細胞", "D": "室管膜細胞"}, "options_image": null},
    {"id": 6, "question": "在中樞神經系統中形成髓鞘的細胞是？", "question_image": null, "options": {"A": "許旺氏細胞", "B": "寡突膠細胞", "C": "星形膠細胞", "D": "微膠細胞"}, "options_image": null},
    {"id": 7, "question": "在周邊神經系統中形成髓鞘的細胞是？", "question_image": null, "options": {"A": "寡突膠細胞", "B": "許旺氏細胞", "C": "衛星細胞", "D": "星形膠細胞"}, "options_image": null},
    {"id": 8, "question": "神經系統中具有吞噬功能的細胞是？", "question_image": null, "options": {"A": "星形膠細胞", "B": "寡突膠細胞", "C": "微膠細胞", "D": "室管膜細胞"}, "options_image": null},
    {"id": 9, "question": "神經元的基本構造不包括下列何者？", "question_image": "https://lt4.mynet.com.tw/linebot/images/ch8-q9-neuron-structure.png", "options": {"A": "細胞體", "B": "樹突", "C": "軸突", "D": "髓鞘"}, "options_image": null},
    {"id": 10, "question": "神經元中接收訊息的構造主要是？", "question_image": null, "options": {"A": "細胞體", "B": "樹突", "C": "軸突", "D": "突觸端球"}, "options_image": null},
    {"id": 11, "question": "神經元中傳出訊息的構造是？", "question_image": null, "options": {"A": "樹突", "B": "軸突", "C": "細胞體", "D": "尼氏體"}, "options_image": null},
    {"id": 12, "question": "髓鞘的功能是？", "question_image": null, "options": {"A": "產生動作電位", "B": "加速神經衝動傳導", "C": "接收訊息", "D": "合成神經傳遞物質"}, "options_image": null},
    {"id": 13, "question": "蘭氏結是指？", "question_image": "https://lt4.mynet.com.tw/linebot/images/ch8-q13-nodes-of-ranvier.png", "options": {"A": "髓鞘覆蓋的區域", "B": "髓鞘之間的缺口", "C": "神經元之間的連接", "D": "軸突末端"}, "options_image": null},
    {"id": 14, "question": "白質是由下列何者組成？", "question_image": null, "options": {"A": "神經元細胞體", "B": "有髓鞘的軸突", "C": "樹突", "D": "神經膠細胞體"}, "options_image": null},
    {"id": 15, "question": "灰質是由下列何者組成？", "question_image": null, "options": {"A": "有髓鞘的軸突", "B": "神經元細胞體和樹突", "C": "許旺氏細胞", "D": "蘭氏結"}, "options_image": null},
    {"id": 16, "question": "神經元靜止膜電位約為？", "question_image": null, "options": {"A": "+70 mV", "B": "-70 mV", "C": "0 mV", "D": "+30 mV"}, "options_image": null},
    {"id": 17, "question": "維持靜止膜電位的主要機制是？", "question_image": null, "options": {"A": "鈣離子通道", "B": "鈉鉀幫浦", "C": "氯離子通道", "D": "水通道"}, "options_image": null},
    {"id": 18, "question": "動作電位的去極化階段主要是因為？", "question_image": "https://lt4.mynet.com.tw/linebot/images/ch8-q18-action-potential.png", "options": {"A": "鉀離子流出", "B": "鈉離子流入", "C": "鈣離子流入", "D": "氯離子流入"}, "options_image": null},
    {"id": 19, "question": "動作電位的再極化階段主要是因為？", "question_image": null, "options": {"A": "鈉離子流入", "B": "鉀離子流出", "C": "鈣離子流入", "D": "鈉離子流出"}, "options_image": null},
    {"id": 20, "question": "過極化是指？", "question_image": null, "options": {"A": "膜電位比靜止膜電位更正", "B": "膜電位比靜止膜電位更負", "C": "膜電位等於零", "D": "膜電位等於靜止膜電位"}, "options_image": null},
    {"id": 21, "question": "絕對不反應期是指？", "question_image": null, "options": {"A": "無論多強的刺激都無法引發新的動作電位", "B": "需要較強刺激才能引發動作電位", "C": "可正常產生動作電位", "D": "膜電位為零"}, "options_image": null},
    {"id": 22, "question": "有髓鞘神經的傳導方式稱為？", "question_image": null, "options": {"A": "連續傳導", "B": "跳躍傳導", "C": "逆向傳導", "D": "雙向傳導"}, "options_image": null},
    {"id": 23, "question": "下列何者可加速神經衝動傳導？(1)增加軸突直徑 (2)有髓鞘 (3)降低溫度", "question_image": null, "options": {"A": "僅(1)", "B": "(1)(2)", "C": "(2)(3)", "D": "(1)(2)(3)"}, "options_image": null},
    {"id": 24, "question": "化學突觸中，神經傳遞物質儲存於？", "question_image": "https://lt4.mynet.com.tw/linebot/images/ch8-q24-synapse.png", "options": {"A": "樹突", "B": "突觸囊泡", "C": "突觸後膜", "D": "突觸間隙"}, "options_image": null},
    {"id": 25, "question": "神經傳遞物質與下列何者結合產生反應？", "question_image": null, "options": {"A": "突觸前膜受器", "B": "突觸後膜受器", "C": "離子幫浦", "D": "粒線體"}, "options_image": null},
    {"id": 26, "question": "保護腦部的三層膜由外而內依序是？", "question_image": null, "options": {"A": "蛛網膜→硬腦膜→軟腦膜", "B": "硬腦膜→軟腦膜→蛛網膜", "C": "硬腦膜→蛛網膜→軟腦膜", "D": "軟腦膜→蛛網膜→硬腦膜"}, "options_image": null},
    {"id": 27, "question": "腦脊髓液位於哪個空間？", "question_image": null, "options": {"A": "硬腦膜上腔", "B": "硬腦膜下腔", "C": "蛛網膜下腔", "D": "軟腦膜下腔"}, "options_image": null},
    {"id": 28, "question": "腦脊髓液由下列何者產生？", "question_image": null, "options": {"A": "蛛網膜", "B": "脈絡叢", "C": "軟腦膜", "D": "硬腦膜"}, "options_image": null},
    {"id": 29, "question": "腦幹由下而上依序是？", "question_image": "https://lt4.mynet.com.tw/linebot/images/ch8-q29-brainstem.png", "options": {"A": "延腦→橋腦→中腦", "B": "中腦→橋腦→延腦", "C": "橋腦→延腦→中腦", "D": "延腦→中腦→橋腦"}, "options_image": null},
    {"id": 30, "question": "控制心跳、呼吸、血壓的生命中樞位於？", "question_image": null, "options": {"A": "中腦", "B": "橋腦", "C": "延腦", "D": "間腦"}, "options_image": null},
    {"id": 31, "question": "視丘的主要功能是？", "question_image": null, "options": {"A": "調節體溫", "B": "感覺訊息的中繼站", "C": "控制呼吸", "D": "維持平衡"}, "options_image": null},
    {"id": 32, "question": "下視丘的功能不包括下列何者？", "question_image": null, "options": {"A": "體溫調節", "B": "飢餓與口渴調節", "C": "語言理解", "D": "內分泌調節"}, "options_image": null},
    {"id": 33, "question": "小腦的主要功能是？", "question_image": null, "options": {"A": "思考判斷", "B": "協調運動與維持平衡", "C": "控制內臟", "D": "感覺訊息處理"}, "options_image": null},
    {"id": 34, "question": "大腦皮質的運動區位於？", "question_image": "https://lt4.mynet.com.tw/linebot/images/ch8-q34-brain-lobes.png", "options": {"A": "額葉", "B": "頂葉", "C": "顳葉", "D": "枕葉"}, "options_image": null},
    {"id": 35, "question": "大腦皮質的感覺區主要位於？", "question_image": null, "options": {"A": "額葉", "B": "頂葉", "C": "顳葉", "D": "枕葉"}, "options_image": null},
    {"id": 36, "question": "視覺區位於大腦的哪個葉？", "question_image": null, "options": {"A": "額葉", "B": "頂葉", "C": "顳葉", "D": "枕葉"}, "options_image": null},
    {"id": 37, "question": "聽覺區位於大腦的哪個葉？", "question_image": null, "options": {"A": "額葉", "B": "頂葉", "C": "顳葉", "D": "枕葉"}, "options_image": null},
    {"id": 38, "question": "基底核的主要功能是？", "question_image": null, "options": {"A": "調節自主運動", "B": "產生情緒", "C": "處理視覺", "D": "控制呼吸"}, "options_image": null},
    {"id": 39, "question": "邊緣系統的功能主要與下列何者有關？", "question_image": null, "options": {"A": "視覺", "B": "情緒與記憶", "C": "聽覺", "D": "運動"}, "options_image": null},
    {"id": 40, "question": "脊髓中灰質呈什麼形狀？", "question_image": "https://lt4.mynet.com.tw/linebot/images/ch8-q40-spinal-cord.png", "options": {"A": "圓形", "B": "H形或蝴蝶形", "C": "三角形", "D": "方形"}, "options_image": null},
    {"id": 41, "question": "脊髓後角主要含有什麼神經元？", "question_image": null, "options": {"A": "運動神經元", "B": "感覺神經元", "C": "聯絡神經元", "D": "自主神經元"}, "options_image": null},
    {"id": 42, "question": "脊髓前角主要含有什麼神經元？", "question_image": null, "options": {"A": "感覺神經元", "B": "運動神經元", "C": "交感神經元", "D": "副交感神經元"}, "options_image": null},
    {"id": 43, "question": "人體有幾對腦神經？", "question_image": null, "options": {"A": "10對", "B": "12對", "C": "31對", "D": "33對"}, "options_image": null},
    {"id": 44, "question": "人體有幾對脊神經？", "question_image": null, "options": {"A": "12對", "B": "24對", "C": "31對", "D": "33對"}, "options_image": null},
    {"id": 45, "question": "第十對腦神經（迷走神經）屬於？", "question_image": null, "options": {"A": "純感覺神經", "B": "純運動神經", "C": "混合神經", "D": "自主神經"}, "options_image": null},
    {"id": 46, "question": "支配上肢運動的神經叢是？", "question_image": null, "options": {"A": "頸神經叢", "B": "臂神經叢", "C": "腰神經叢", "D": "薦神經叢"}, "options_image": null},
    {"id": 47, "question": "交感神經系統的節前神經元位於脊髓的哪個區域？", "question_image": null, "options": {"A": "頸髓", "B": "胸髓和腰髓(T1-L2)", "C": "薦髓", "D": "全部脊髓"}, "options_image": null},
    {"id": 48, "question": "副交感神經系統的神經傳遞物質是？", "question_image": null, "options": {"A": "正腎上腺素", "B": "乙醯膽鹼", "C": "多巴胺", "D": "血清素"}, "options_image": null},
    {"id": 49, "question": "交感神經興奮時，下列何者會發生？", "question_image": null, "options": {"A": "心跳減慢", "B": "瞳孔縮小", "C": "支氣管擴張", "D": "腸胃蠕動增加"}, "options_image": null},
    {"id": 50, "question": "副交感神經興奮時，下列何者會發生？", "question_image": null, "options": {"A": "心跳加快", "B": "瞳孔放大", "C": "腸胃蠕動增加", "D": "支氣管擴張"}, "options_image": null}
  ]
}
